unicorespawner/__init__.py
unicorespawner/_version.py
unicorespawner/api_notifications.py
unicorespawner/spawner.py
jupyterhub_unicorespawner-2.1.0.dist-info/METADATA
jupyterhub_unicorespawner-2.1.0.dist-info/WHEEL
jupyterhub_unicorespawner-2.1.0.dist-info/licenses/LICENSE
jupyterhub_unicorespawner-2.1.0.dist-info/RECORD
