Metadata-Version: 2.4
Name: jupyterhub-unicorespawner
Version: 2.1.0
Summary: JupyterHub Spawner for UNICORE
Author-email: Tim Kreuzer <t.kreuzer@fz-juelich.de>
License: BSD 3-Clause License
License-File: LICENSE
Keywords: jupyterhub,spawner,unicore
Requires-Python: >=3.9
Requires-Dist: aiohttp
Requires-Dist: escapism
Requires-Dist: jinja2
Requires-Dist: jupyterhub-forwardbasespawner>=2.0.0
Requires-Dist: jupyterhub>=5.0.0
Requires-Dist: oauthenticator
Requires-Dist: pyunicore
Requires-Dist: traitlets
Requires-Dist: urllib3
